setup.cfg
setup.py
engchecker2flycheck/__init__.py
engchecker2flycheck/afterthedeadlineapiclient.py
engchecker2flycheck.egg-info/PKG-INFO
engchecker2flycheck.egg-info/SOURCES.txt
engchecker2flycheck.egg-info/dependency_links.txt
engchecker2flycheck.egg-info/top_level.txt
scripts/afterthedeadlinechkfile
scripts/linkgrammarengchkfile
scripts/textgearschkfile