Metadata-Version: 1.1
Name: engchecker2flycheck
Version: 0.0.2
Summary: english grammar cheker interfece to emacs flycheck
Home-page: https://github.com/niitsuma/engchecker2flycheck
Author: Hirotaka Niitsuma
Author-email: hirotaka.niitsuma@gmail.com
License: GNU Affero General Public License, version 3 - http://www.gnu.org/licenses/agpl-3.0.html
Download-URL: https://github.com/niitsuma/engchecker2flycheck/archive/master.zip
Platform: UNKNOWN
